cli.py
મુખ્ય.py
gujarati_python-1.2.0.dist-info/licenses/LICENSE
ગુજરાતી_પાઈથન/__init__.py
ગુજરાતી_પાઈથન/અનુવાદક.py
ગુજરાતી_પાઈથન/પ્રોસેસર.py
ગુજરાતી_પાઈથન/ભૂલ_અનુવાદક.py
ગુજરાતી_પાઈથન/સહાયકો.py
ટેસ્ટ/__init__.py
ટેસ્ટ/ઉદાહરણ_ટેસ્ટ.py
ટેસ્ટ/ટેસ્ટ_અનુવાદક.py
ટેસ્ટ/પ્લેટફોર્મ_ટેસ્ટ.py
gujarati_python-1.2.0.dist-info/METADATA
gujarati_python-1.2.0.dist-info/WHEEL
gujarati_python-1.2.0.dist-info/entry_points.txt
gujarati_python-1.2.0.dist-info/top_level.txt
gujarati_python-1.2.0.dist-info/RECORD
