Metadata-Version: 2.4
Name: gujarati-python
Version: 1.2.0
Summary: Python programming with complete Gujarati syntax and keywords
Home-page: https://github.com/ambicuity/gujarati-python
Author: Ritesh Rana
Author-email: contact@riteshrana.engineer
Project-URL: Bug Reports, https://github.com/ambicuity/gujarati-python/issues
Project-URL: Source, https://github.com/ambicuity/gujarati-python
Project-URL: Documentation, https://github.com/ambicuity/gujarati-python/tree/main/ડોક્સ
Keywords: gujarati python programming language localization
Classifier: Development Status :: 4 - Beta
Classifier: Intended Audience :: Developers
Classifier: Intended Audience :: Education
Classifier: Topic :: Software Development :: Interpreters
Classifier: Topic :: Software Development :: Localization
Classifier: License :: OSI Approved :: Apache Software License
Classifier: Programming Language :: Python :: 3
Classifier: Programming Language :: Python :: 3.6
Classifier: Programming Language :: Python :: 3.7
Classifier: Programming Language :: Python :: 3.8
Classifier: Programming Language :: Python :: 3.9
Classifier: Programming Language :: Python :: 3.10
Classifier: Programming Language :: Python :: 3.11
Classifier: Programming Language :: Python :: 3.12
Classifier: Operating System :: OS Independent
Requires-Python: >=3.6
License-File: LICENSE
Requires-Dist: rich>=13.0.0
Dynamic: author
Dynamic: author-email
Dynamic: classifier
Dynamic: description
Dynamic: description-content-type
Dynamic: home-page
Dynamic: keywords
Dynamic: license-file
Dynamic: project-url
Dynamic: requires-dist
Dynamic: requires-python
Dynamic: summary
